{
  "countries": [
    {
      "name": "Rwanda",
      "code": "RW",
      "currency": "RWF",
      "continent": "Africa",
      "essentialInfo": {
        "fiscalYear": "July to June",
        "taxAuthority": "Rwanda Revenue Authority (RRA)",
        "filingDeadline": "15th of the following month"
      },
      "taxes": [
        {
          "name": "Value Added Tax",
          "type": "VAT",
          "rate": 18,
          "unit": "percent",
          "description": "Standard consumption tax on goods and services.",
          "authority": "RRA",
          "id": "3240b379-4bc5-4010-a6f8-ff0091528e72"
        },
        {
          "name": "Pay As You Earn",
          "type": "PAYE",
          "rate": "0-30",
          "unit": "percent",
          "description": "Progressive tax on employment income.",
          "bands": [
            {
              "min": 0,
              "max": 60000,
              "rate": 0,
              "label": "Exempt"
            },
            {
              "min": 60001,
              "max": 100000,
              "rate": 0.1,
              "label": "First Band"
            },
            {
              "min": 100001,
              "max": 200000,
              "rate": 0.2,
              "label": "Second Band"
            },
            {
              "min": 200001,
              "max": null,
              "rate": 0.3,
              "label": "Third Band"
            }
          ],
          "id": "85b1ebcb-ac91-4113-a979-285cad03dd6f"
        },
        {
          "name": "Pension Contribution",
          "type": "RSSB",
          "rate": 3,
          "unit": "percent",
          "description": "Mandatory pension contribution for employees.",
          "id": "04f7a276-2c77-4fed-a1a1-768392217144"
        },
        {
          "name": "Maternity Leave Fund",
          "type": "RSSB_MATERNITY",
          "rate": 0.3,
          "unit": "percent",
          "description": "Social security fund for maternity benefits.",
          "id": "06363788-37b9-4969-a8ae-ed8adb91c8f9"
        },
        {
          "name": "Withholding Tax",
          "type": "WHT",
          "rate": 15,
          "unit": "percent",
          "description": "Standard WHT on professional services and management fees.",
          "id": "da2baf84-57fe-44e8-8c19-267ba4eee91e"
        },
        {
          "name": "Corporate Income Tax",
          "type": "CIT",
          "rate": 28,
          "unit": "percent",
          "id": "9f70631a-21fd-43ff-ab7b-3aed352c6618"
        }
      ]
    },
    {
      "name": "Kenya",
      "code": "KE",
      "currency": "KES",
      "continent": "Africa",
      "essentialInfo": {
        "fiscalYear": "July to June",
        "taxAuthority": "Kenya Revenue Authority (KRA)",
        "filingDeadline": "20th of the following month"
      },
      "taxes": [
        {
          "name": "Value Added Tax",
          "type": "VAT",
          "rate": 16,
          "unit": "percent",
          "description": "Standard rate for taxable supplies.",
          "id": "08b916a7-e12e-4176-beed-251df23e0cf9"
        },
        {
          "name": "Personal Income Tax",
          "type": "PAYE",
          "rate": "10-35",
          "unit": "percent",
          "bands": [
            {
              "min": 0,
              "max": 288000,
              "rate": 0.1,
              "label": "First Band"
            },
            {
              "min": 288001,
              "max": 388000,
              "rate": 0.25,
              "label": "Second Band"
            },
            {
              "min": 388001,
              "max": 6000000,
              "rate": 0.3,
              "label": "Third Band"
            },
            {
              "min": 6000001,
              "max": 9600000,
              "rate": 0.325,
              "label": "Fourth Band"
            },
            {
              "min": 9600001,
              "max": null,
              "rate": 0.35,
              "label": "Fifth Band"
            }
          ],
          "id": "edada365-f511-41a3-b804-071520d1a088"
        },
        {
          "name": "Corporate Tax (Resident)",
          "type": "CIT",
          "rate": 30,
          "unit": "percent",
          "id": "4c2a746b-5af7-479f-9198-40a58847f556"
        }
      ]
    },
    {
      "name": "Uganda",
      "code": "UG",
      "currency": "UGX",
      "continent": "Africa",
      "essentialInfo": {
        "fiscalYear": "July to June",
        "taxAuthority": "Uganda Revenue Authority (URA)",
        "filingDeadline": "15th of the following month"
      },
      "taxes": [
        {
          "name": "Value Added Tax",
          "type": "VAT",
          "rate": 18,
          "unit": "percent",
          "id": "7df86157-625c-44d1-a0a4-399249ad93e3"
        },
        {
          "name": "Pay As You Earn",
          "type": "PAYE",
          "rate": "0-40",
          "unit": "percent",
          "bands": [
            {
              "min": 0,
              "max": 2820000,
              "rate": 0
            },
            {
              "min": 2820001,
              "max": 4020000,
              "rate": 0.1
            },
            {
              "min": 4020001,
              "max": 4920000,
              "rate": 0.2
            },
            {
              "min": 4920001,
              "max": 12000000,
              "rate": 0.3
            },
            {
              "min": 12000001,
              "max": null,
              "rate": 0.4
            }
          ],
          "id": "a0d3058a-b81b-41bf-bcfb-fca455719770"
        },
        {
          "name": "Corporate Tax",
          "type": "CIT",
          "rate": 30,
          "unit": "percent",
          "id": "a0d3058a-b81b-41bf-bcfb-fca455719771"
        }
      ]
    },
    {
      "name": "South Africa",
      "code": "ZA",
      "currency": "ZAR",
      "continent": "Africa",
      "essentialInfo": {
        "fiscalYear": "March to February",
        "taxAuthority": "South African Revenue Service (SARS)",
        "filingDeadline": "Varies (Sept-Jan for individuals)"
      },
      "taxes": [
        {
          "name": "Value Added Tax",
          "type": "VAT",
          "rate": 15,
          "unit": "percent",
          "id": "62afe6dc-0fdc-479a-911f-3cf74cd153bc"
        },
        {
          "name": "Individual Income Tax",
          "type": "PAYE",
          "rate": "18-45",
          "unit": "percent",
          "id": "729f8161-226d-47f7-8670-351cfd40979f"
        },
        {
          "name": "Corporate Tax",
          "type": "CIT",
          "rate": 27,
          "unit": "percent",
          "id": "da5d86e9-7c15-4b66-a4ca-b175dd8f7bb7"
        }
      ]
    },
    {
      "name": "United Kingdom",
      "code": "GB",
      "currency": "GBP",
      "continent": "Europe",
      "essentialInfo": {
        "fiscalYear": "April to April",
        "taxAuthority": "HM Revenue & Customs (HMRC)",
        "filingDeadline": "31 January (online)"
      },
      "taxes": [
        {
          "id": "e4a2d3c1-b3b3-4f9e-9d2a-4a2b3c4d5e6f",
          "name": "Value Added Tax",
          "type": "VAT",
          "rate": 20,
          "unit": "percent"
        },
        {
          "id": "f5b3e4d2-c4c4-5a0f-0e3b-5b3c4d5e6f7a",
          "name": "Income Tax",
          "type": "PAYE",
          "rate": "20-45",
          "unit": "percent",
          "bands": [
            {
              "min": 0,
              "max": 12570,
              "rate": 0,
              "label": "Personal Allowance"
            },
            {
              "min": 12571,
              "max": 50270,
              "rate": 0.2,
              "label": "Basic Rate"
            },
            {
              "min": 50271,
              "max": 125140,
              "rate": 0.4,
              "label": "Higher Rate"
            },
            {
              "min": 125141,
              "max": null,
              "rate": 0.45,
              "label": "Additional Rate"
            }
          ]
        },
        {
          "id": "g6c4f5e3-d5d5-6b1e-0f4c-6c4d5e6f7a8b",
          "name": "Corporation Tax",
          "type": "CIT",
          "rate": 25,
          "unit": "percent"
        }
      ]
    },
    {
      "name": "United States",
      "code": "US",
      "currency": "USD",
      "continent": "North America",
      "essentialInfo": {
        "fiscalYear": "January to December",
        "taxAuthority": "Internal Revenue Service (IRS)",
        "filingDeadline": "April 15"
      },
      "taxes": [
        {
          "name": "Federal Income Tax",
          "type": "INCOME",
          "rate": "10-37",
          "unit": "percent",
          "id": "f12d9d1e-de59-470d-85d2-764fb950609a"
        },
        {
          "name": "Corporate Tax",
          "type": "CIT",
          "rate": 21,
          "unit": "percent",
          "id": "95dc47b2-0220-4950-a400-6519ffc94e37"
        }
      ]
    },
    {
      "name": "Nigeria",
      "code": "NG",
      "currency": "NGN",
      "continent": "Africa",
      "essentialInfo": {
        "fiscalYear": "January to December",
        "taxAuthority": "Nigeria Revenue Service (NRS)",
        "filingDeadline": "30th June"
      },
      "taxes": [
        {
          "id": "addfa5ec-4022-4a9c-9926-22af89218bbd",
          "name": "Value Added Tax",
          "type": "VAT",
          "rate": 7.5,
          "unit": "percent",
          "description": "Consumption tax on goods and services."
        },
        {
          "id": "e03d7782-cb7e-4a0c-a666-ff3c689946a4",
          "name": "Personal Income Tax",
          "type": "PAYE",
          "rate": "0-25",
          "unit": "percent",
          "bands": [
            {
              "min": 0,
              "max": 800000,
              "rate": 0,
              "label": "Exempt"
            },
            {
              "min": 800001,
              "max": 3000000,
              "rate": 0.15,
              "label": "First Band"
            },
            {
              "min": 3000001,
              "max": 12000000,
              "rate": 0.18,
              "label": "Second Band"
            },
            {
              "min": 12000001,
              "max": 25000000,
              "rate": 0.21,
              "label": "Third Band"
            },
            {
              "min": 25000001,
              "max": 50000000,
              "rate": 0.23,
              "label": "Fourth Band"
            },
            {
              "min": 50000001,
              "max": null,
              "rate": 0.25,
              "label": "Fifth Band"
            }
          ]
        },
        {
          "id": "baa81723-3b9f-4e88-a367-db32471be666",
          "name": "Company Income Tax",
          "type": "CIT",
          "rate": 30,
          "unit": "percent"
        }
      ]
    },
    {
      "name": "Ghana",
      "code": "GH",
      "currency": "GHS",
      "continent": "Africa",
      "essentialInfo": {
        "fiscalYear": "January to December",
        "taxAuthority": "Ghana Revenue Authority (GRA)",
        "filingDeadline": "30th April"
      },
      "taxes": [
        {
          "id": "5a1f8655-51df-41d3-9cef-340d2b3e9bb0",
          "name": "Value Added Tax",
          "type": "VAT",
          "rate": 20,
          "unit": "percent",
          "description": "Standard VAT rate comprising 15% VAT, 2.5% NHIL, and 2.5% GETFund."
        },
        {
          "id": "9f4dd49e-9f70-42ad-9a06-f21b335d8eef",
          "name": "Individual Income Tax",
          "type": "PAYE",
          "rate": "0-35",
          "unit": "percent",
          "bands": [
            {
              "min": 0,
              "max": 5880,
              "rate": 0,
              "label": "Exempt"
            },
            {
              "min": 5881,
              "max": 7200,
              "rate": 0.05
            },
            {
              "min": 7201,
              "max": 8880,
              "rate": 0.1
            },
            {
              "min": 8881,
              "max": 42000,
              "rate": 0.175
            },
            {
              "min": 42001,
              "max": 240000,
              "rate": 0.25
            },
            {
              "min": 240001,
              "max": 600000,
              "rate": 0.3
            },
            {
              "min": 600001,
              "max": null,
              "rate": 0.35
            }
          ]
        },
        {
          "id": "66c9c551-a6c6-4178-bea9-82e39b8609b5",
          "name": "Corporate Income Tax",
          "type": "CIT",
          "rate": 25,
          "unit": "percent"
        }
      ]
    },
    {
      "name": "Tanzania",
      "code": "TZ",
      "currency": "TZS",
      "continent": "Africa",
      "essentialInfo": {
        "fiscalYear": "July to June",
        "taxAuthority": "Tanzania Revenue Authority (TRA)",
        "filingDeadline": "31st March"
      },
      "taxes": [
        {
          "id": "a07a15b4-92bc-4e4f-a7e5-65409d769993",
          "name": "Value Added Tax",
          "type": "VAT",
          "rate": 18,
          "unit": "percent"
        },
        {
          "id": "741a84a7-1006-4e4f-b61c-647fb9129b10",
          "name": "Individual Income Tax",
          "type": "PAYE",
          "rate": "0-30",
          "unit": "percent",
          "bands": [
            {
              "min": 0,
              "max": 270000,
              "rate": 0
            },
            {
              "min": 270001,
              "max": 520000,
              "rate": 0.08
            },
            {
              "min": 520001,
              "max": 760000,
              "rate": 0.2
            },
            {
              "min": 760001,
              "max": 1000000,
              "rate": 0.25
            },
            {
              "min": 1000001,
              "max": null,
              "rate": 0.3
            }
          ]
        },
        {
          "id": "0ef1e9ae-7e00-4e99-93b4-c246d6c87a4c",
          "name": "Corporate Tax",
          "type": "CIT",
          "rate": 30,
          "unit": "percent"
        }
      ]
    },
    {
      "name": "Ethiopia",
      "code": "ET",
      "currency": "ETB",
      "continent": "Africa",
      "essentialInfo": {
        "fiscalYear": "July to July",
        "taxAuthority": "Ministry of Revenues",
        "filingDeadline": "Varies"
      },
      "taxes": [
        {
          "id": "a4a027cb-db91-4e22-886c-21c61a00f144",
          "name": "Value Added Tax",
          "type": "VAT",
          "rate": 15,
          "unit": "percent"
        },
        {
          "id": "274dc90d-22c2-479e-b0cd-2dae0b6c23fa",
          "name": "Employment Income Tax",
          "type": "PAYE",
          "rate": "0-35",
          "unit": "percent",
          "bands": [
            {
              "min": 0,
              "max": 2000,
              "rate": 0
            },
            {
              "min": 2001,
              "max": 4000,
              "rate": 0.15
            },
            {
              "min": 4001,
              "max": 7000,
              "rate": 0.2
            },
            {
              "min": 7001,
              "max": 10000,
              "rate": 0.25
            },
            {
              "min": 10001,
              "max": 14000,
              "rate": 0.3
            },
            {
              "min": 14001,
              "max": null,
              "rate": 0.35
            }
          ]
        },
        {
          "id": "8c1fc5c7-518b-492c-bde4-7ee9aadc89a7",
          "name": "Business Income Tax",
          "type": "CIT",
          "rate": 30,
          "unit": "percent"
        }
      ]
    },
    {
      "name": "Egypt",
      "code": "EG",
      "currency": "EGP",
      "continent": "Africa",
      "essentialInfo": {
        "fiscalYear": "January to December",
        "taxAuthority": "National Revenue Authority",
        "filingDeadline": "Variable"
      },
      "taxes": [
        {
          "id": "0d1c6832-b30f-40db-afb1-39c61d0f694b",
          "name": "Value Added Tax",
          "type": "VAT",
          "rate": 14,
          "unit": "percent"
        },
        {
          "id": "18f00fa4-f591-424e-a1a4-b7992131973b",
          "name": "Corporate Income Tax",
          "type": "CIT",
          "rate": 22.5,
          "unit": "percent"
        },
        {
          "id": "18f00fa4-f591-424e-a1a4-b7992131973c",
          "name": "Personal Income Tax",
          "type": "PAYE",
          "rate": "10-27.5",
          "unit": "percent"
        }
      ]
    },
    {
      "name": "Morocco",
      "code": "MA",
      "currency": "MAD",
      "continent": "Africa",
      "essentialInfo": {
        "fiscalYear": "January to December",
        "taxAuthority": "National Revenue Authority",
        "filingDeadline": "Variable"
      },
      "taxes": [
        {
          "id": "fb2e2a6c-a420-4cf5-849d-0104ceae0e27",
          "name": "Value Added Tax",
          "type": "VAT",
          "rate": 20,
          "unit": "percent"
        },
        {
          "id": "31d99369-2630-4e1e-901f-2fb227d95331",
          "name": "Corporate Income Tax",
          "type": "CIT",
          "rate": 20,
          "unit": "percent"
        },
        {
          "id": "31d99369-2630-4e1e-901f-2fb227d95332",
          "name": "Personal Income Tax",
          "type": "PAYE",
          "rate": "0-37",
          "unit": "percent"
        }
      ]
    },
    {
      "name": "Senegal",
      "code": "SN",
      "currency": "XOF",
      "continent": "Africa",
      "essentialInfo": {
        "fiscalYear": "January to December",
        "taxAuthority": "National Revenue Authority",
        "filingDeadline": "Variable"
      },
      "taxes": [
        {
          "id": "960aab87-ef1e-44d3-b918-f7dbbcb0b75c",
          "name": "Value Added Tax",
          "type": "VAT",
          "rate": 18,
          "unit": "percent"
        },
        {
          "id": "cd919cc8-282e-48d6-a32b-7a58db94b596",
          "name": "Corporate Income Tax",
          "type": "CIT",
          "rate": 30,
          "unit": "percent"
        },
        {
          "id": "cd919cc8-282e-48d6-a32b-7a58db94b597",
          "name": "Personal Income Tax",
          "type": "PAYE",
          "rate": "0-43",
          "unit": "percent"
        }
      ]
    },
    {
      "name": "Cote d'Ivoire",
      "code": "CI",
      "currency": "XOF",
      "continent": "Africa",
      "essentialInfo": {
        "fiscalYear": "January to December",
        "taxAuthority": "National Revenue Authority",
        "filingDeadline": "Variable"
      },
      "taxes": [
        {
          "id": "d4339243-cdbd-48bd-8f3d-6094d9cb238a",
          "name": "Value Added Tax",
          "type": "VAT",
          "rate": 18,
          "unit": "percent"
        },
        {
          "id": "13d179e3-effc-459d-b972-447fc2e5e4b9",
          "name": "Corporate Income Tax",
          "type": "CIT",
          "rate": 25,
          "unit": "percent"
        }
      ]
    },
    {
      "name": "Cameroon",
      "code": "CM",
      "currency": "XAF",
      "continent": "Africa",
      "essentialInfo": {
        "fiscalYear": "January to December",
        "taxAuthority": "National Revenue Authority",
        "filingDeadline": "Variable"
      },
      "taxes": [
        {
          "id": "28cb33d0-f256-4543-8204-3fa0756f6a6c",
          "name": "Value Added Tax",
          "type": "VAT",
          "rate": 19.25,
          "unit": "percent"
        },
        {
          "id": "814653aa-2bdd-4c39-8ca1-8231ac8d0657",
          "name": "Corporate Income Tax",
          "type": "CIT",
          "rate": 33,
          "unit": "percent"
        },
        {
          "id": "814653aa-2bdd-4c39-8ca1-8231ac8d0658",
          "name": "Personal Income Tax",
          "type": "PAYE",
          "rate": "11-38.5",
          "unit": "percent"
        }
      ]
    },
    {
      "name": "Zimbabwe",
      "code": "ZW",
      "currency": "ZWL",
      "continent": "Africa",
      "essentialInfo": {
        "fiscalYear": "January to December",
        "taxAuthority": "National Revenue Authority",
        "filingDeadline": "Variable"
      },
      "taxes": [
        {
          "id": "0c51f62d-cc55-4261-b7de-76f9b3389da8",
          "name": "Value Added Tax",
          "type": "VAT",
          "rate": 15.5,
          "unit": "percent"
        },
        {
          "id": "009676c1-fe92-4ec2-bc12-8c1cd5438774",
          "name": "Corporate Income Tax",
          "type": "CIT",
          "rate": 25,
          "unit": "percent"
        },
        {
          "id": "009676c1-fe92-4ec2-bc12-8c1cd5438775",
          "name": "Personal Income Tax",
          "type": "PAYE",
          "rate": "0-40",
          "unit": "percent"
        }
      ]
    },
    {
      "name": "Mauritius",
      "code": "MU",
      "currency": "MUR",
      "continent": "Africa",
      "essentialInfo": {
        "fiscalYear": "January to December",
        "taxAuthority": "National Revenue Authority",
        "filingDeadline": "Variable"
      },
      "taxes": [
        {
          "id": "5f537553-281c-4289-a505-6b242e4647fc",
          "name": "Value Added Tax",
          "type": "VAT",
          "rate": 15,
          "unit": "percent"
        },
        {
          "id": "059cd54d-53a6-4a59-bbbc-76686ba6637f",
          "name": "Corporate Income Tax",
          "type": "CIT",
          "rate": 15,
          "unit": "percent"
        },
        {
          "id": "059cd54d-53a6-4a59-bbbc-76686ba6637e",
          "name": "Personal Income Tax",
          "type": "PAYE",
          "rate": "0-20",
          "unit": "percent",
          "bands": [
            {
              "min": 0,
              "max": 500000,
              "rate": 0
            },
            {
              "min": 500001,
              "max": 1000000,
              "rate": 0.1
            },
            {
              "min": 1000001,
              "max": null,
              "rate": 0.2
            }
          ]
        }
      ]
    },
    {
      "name": "Algeria",
      "code": "DZ",
      "currency": "DZD",
      "continent": "Africa",
      "essentialInfo": {
        "fiscalYear": "January to December",
        "taxAuthority": "National Revenue Authority",
        "filingDeadline": "Variable"
      },
      "taxes": [
        {
          "id": "3e9cfd3c-e7a1-40dc-91a4-3e2a53cd7e7a",
          "name": "Value Added Tax",
          "type": "VAT",
          "rate": 19,
          "unit": "percent"
        },
        {
          "id": "286d0304-0b9b-4207-afe8-db20087141af",
          "name": "Corporate Income Tax",
          "type": "CIT",
          "rate": 26,
          "unit": "percent"
        },
        {
          "id": "286d0304-0b9b-4207-afe8-db20087141ae",
          "name": "Personal Income Tax",
          "type": "PAYE",
          "rate": "0-35",
          "unit": "percent"
        }
      ]
    },
    {
      "name": "Tunisia",
      "code": "TN",
      "currency": "TND",
      "continent": "Africa",
      "essentialInfo": {
        "fiscalYear": "January to December",
        "taxAuthority": "National Revenue Authority",
        "filingDeadline": "Variable"
      },
      "taxes": [
        {
          "id": "d58992a5-4304-499a-810b-4bdab13bea1d",
          "name": "Value Added Tax",
          "type": "VAT",
          "rate": 19,
          "unit": "percent"
        },
        {
          "id": "00081894-c2c2-4df5-9401-7a002fb39cfa",
          "name": "Corporate Income Tax",
          "type": "CIT",
          "rate": 20,
          "unit": "percent"
        },
        {
          "id": "00081894-c2c2-4df5-9401-7a002fb39cfb",
          "name": "Personal Income Tax",
          "type": "PAYE",
          "rate": "0-40",
          "unit": "percent"
        }
      ]
    },
    {
      "name": "France",
      "code": "FR",
      "currency": "EUR",
      "continent": "Europe",
      "essentialInfo": {
        "fiscalYear": "January to December",
        "taxAuthority": "National Revenue Authority",
        "filingDeadline": "Variable"
      },
      "taxes": [
        {
          "id": "03a0e83f-5c9d-4bfe-8229-2d69eeb0adc7",
          "name": "Value Added Tax",
          "type": "VAT",
          "rate": 20,
          "unit": "percent"
        },
        {
          "id": "2dfae818-262b-4815-9106-0daa40a11d47",
          "name": "Corporate Income Tax",
          "type": "CIT",
          "rate": 25.8,
          "unit": "percent"
        },
        {
          "id": "a1b2c3d4-e5f6-4a5b-8c7d-9e0f1a2b3c4d",
          "name": "Income Tax",
          "type": "PAYE",
          "rate": "0-45",
          "unit": "percent",
          "bands": [
            {
              "min": 0,
              "max": 11600,
              "rate": 0
            },
            {
              "min": 11601,
              "max": 29579,
              "rate": 0.11
            },
            {
              "min": 29580,
              "max": 84577,
              "rate": 0.3
            },
            {
              "min": 84578,
              "max": 181917,
              "rate": 0.41
            },
            {
              "min": 181918,
              "max": null,
              "rate": 0.45
            }
          ]
        }
      ]
    },
    {
      "name": "Germany",
      "code": "DE",
      "currency": "EUR",
      "continent": "Europe",
      "essentialInfo": {
        "fiscalYear": "January to December",
        "taxAuthority": "National Revenue Authority",
        "filingDeadline": "Variable"
      },
      "taxes": [
        {
          "id": "dc0b703d-e0de-4fd8-9adf-4de31331954d",
          "name": "Value Added Tax",
          "type": "VAT",
          "rate": 19,
          "unit": "percent"
        },
        {
          "id": "b2c3d4e5-f6a7-4b6c-9d8e-0f1a2b3c4d5e",
          "name": "Income Tax",
          "type": "PAYE",
          "rate": "14-45",
          "unit": "percent",
          "bands": [
            {
              "min": 0,
              "max": 12348,
              "rate": 0,
              "label": "Tax Free"
            },
            {
              "min": 12349,
              "max": 69878,
              "rate": 0.14,
              "label": "Basic"
            },
            {
              "min": 69879,
              "max": 277825,
              "rate": 0.42,
              "label": "Higher"
            },
            {
              "min": 277826,
              "max": null,
              "rate": 0.45,
              "label": "Top"
            }
          ]
        },
        {
          "id": "c3d4e5f6-a7b8-4c7d-0e9f-1a2b3c4d5e6f",
          "name": "Corporate Income Tax",
          "type": "CIT",
          "rate": 15.825,
          "unit": "percent",
          "description": "Statutory rate (15%) plus 5.5% solidarity surcharge."
        }
      ]
    },
    {
      "name": "Italy",
      "code": "IT",
      "currency": "EUR",
      "continent": "Europe",
      "essentialInfo": {
        "fiscalYear": "January to December",
        "taxAuthority": "National Revenue Authority",
        "filingDeadline": "Variable"
      },
      "taxes": [
        {
          "id": "3774aae5-8de9-4074-bc58-d16657b27718",
          "name": "Value Added Tax",
          "type": "VAT",
          "rate": 22,
          "unit": "percent"
        },
        {
          "id": "d4e5f6a7-b8c9-4d8e-1f0g-2b3c4d5e6f7g",
          "name": "Income Tax (IRPEF)",
          "type": "PAYE",
          "rate": "23-43",
          "unit": "percent",
          "bands": [
            {
              "min": 0,
              "max": 28000,
              "rate": 0.23
            },
            {
              "min": 28001,
              "max": 50000,
              "rate": 0.33
            },
            {
              "min": 50001,
              "max": null,
              "rate": 0.43
            }
          ]
        },
        {
          "id": "471b1770-bcc7-406d-b076-53a47495218c",
          "name": "Corporate Income Tax (IRES)",
          "type": "CIT",
          "rate": 24,
          "unit": "percent"
        }
      ]
    },
    {
      "name": "Spain",
      "code": "ES",
      "currency": "EUR",
      "continent": "Europe",
      "essentialInfo": {
        "fiscalYear": "January to December",
        "taxAuthority": "National Revenue Authority",
        "filingDeadline": "Variable"
      },
      "taxes": [
        {
          "id": "2f642bbc-6ac5-4dba-85ad-6e7d267b8120",
          "name": "Value Added Tax",
          "type": "VAT",
          "rate": 21,
          "unit": "percent"
        },
        {
          "id": "e5f6a7b8-c9d0-4e9f-2g1h-3c4d5e6f7g8h",
          "name": "Income Tax (IRPF)",
          "type": "PAYE",
          "rate": "19-47",
          "unit": "percent",
          "bands": [
            {
              "min": 0,
              "max": 12450,
              "rate": 0.19
            },
            {
              "min": 12451,
              "max": 20200,
              "rate": 0.24
            },
            {
              "min": 20201,
              "max": 35200,
              "rate": 0.3
            },
            {
              "min": 35201,
              "max": 60000,
              "rate": 0.37
            },
            {
              "min": 60001,
              "max": 300000,
              "rate": 0.45
            },
            {
              "min": 300001,
              "max": null,
              "rate": 0.47
            }
          ]
        },
        {
          "id": "f9eb13ff-eab8-4c9b-8120-3efd632a37b9",
          "name": "Corporate Income Tax",
          "type": "CIT",
          "rate": 25,
          "unit": "percent"
        }
      ]
    },
    {
      "name": "Netherlands",
      "code": "NL",
      "currency": "EUR",
      "continent": "Europe",
      "essentialInfo": {
        "fiscalYear": "January to December",
        "taxAuthority": "National Revenue Authority",
        "filingDeadline": "Variable"
      },
      "taxes": [
        {
          "id": "6ddd9df0-dcac-45e0-a6e7-7b387e45b49a",
          "name": "Value Added Tax",
          "type": "VAT",
          "rate": 21,
          "unit": "percent"
        },
        {
          "id": "911f30bb-08ee-4eb6-9ded-f0adce21a367",
          "name": "Corporate Income Tax",
          "type": "CIT",
          "rate": 25.8,
          "unit": "percent"
        }
      ]
    },
    {
      "name": "Switzerland",
      "code": "CH",
      "currency": "CHF",
      "continent": "Europe",
      "essentialInfo": {
        "fiscalYear": "January to December",
        "taxAuthority": "National Revenue Authority",
        "filingDeadline": "Variable"
      },
      "taxes": [
        {
          "id": "h8c9d0e1-f2a3-6h2i-5j4k-6f7g8h9i0j1k",
          "name": "Value Added Tax",
          "type": "VAT",
          "rate": 8.1,
          "unit": "percent"
        },
        {
          "id": "i9d0e1f2-a3b4-7i3j-6k5l-7g8h9i0j1k2l",
          "name": "Federal Income Tax",
          "type": "PAYE",
          "rate": "0-11.5",
          "unit": "percent"
        },
        {
          "id": "i9d0e1f2-a3b4-7i3j-6k5l-7g8h9i0j1k2m",
          "name": "Corporate Tax (Total)",
          "type": "CIT",
          "rate": 14.4,
          "unit": "percent",
          "description": "Combined federal, cantonal, and communal average."
        }
      ]
    },
    {
      "name": "Sweden",
      "code": "SE",
      "currency": "SEK",
      "continent": "Europe",
      "essentialInfo": {
        "fiscalYear": "January to December",
        "taxAuthority": "National Revenue Authority",
        "filingDeadline": "Variable"
      },
      "taxes": [
        {
          "id": "52a0ff14-bf6f-43c4-9c94-010048f4c8d1",
          "name": "Value Added Tax",
          "type": "VAT",
          "rate": 25,
          "unit": "percent"
        },
        {
          "id": "k1f2a3b4-c5d6-9k5l-8m7n-9i0j1k2l3m4n",
          "name": "Corporate Income Tax",
          "type": "CIT",
          "rate": 20.6,
          "unit": "percent"
        },
        {
          "id": "j0e1f2a3-b4c5-8j4k-7l6m-8h9i0j1k2l3m",
          "name": "National Income Tax",
          "type": "PAYE",
          "rate": 20,
          "unit": "percent",
          "bands": [
            {
              "min": 0,
              "max": 625800,
              "rate": 0
            },
            {
              "min": 625801,
              "max": null,
              "rate": 0.2
            }
          ]
        }
      ]
    },
    {
      "name": "Norway",
      "code": "NO",
      "currency": "NOK",
      "continent": "Europe",
      "essentialInfo": {
        "fiscalYear": "January to December",
        "taxAuthority": "National Revenue Authority",
        "filingDeadline": "Variable"
      },
      "taxes": [
        {
          "id": "db513679-aa85-4f7f-9ee3-61c0fc41c69f",
          "name": "Value Added Tax",
          "type": "VAT",
          "rate": 25,
          "unit": "percent"
        },
        {
          "id": "l2a3b4c5-d6e7-0l6m-9n8p-0j1k2l3m4n5p",
          "name": "Bracket Tax (Trinnskatt)",
          "type": "PAYE",
          "rate": "1.7-17.8",
          "unit": "percent",
          "bands": [
            {
              "min": 0,
              "max": 226100,
              "rate": 0
            },
            {
              "min": 226101,
              "max": 318300,
              "rate": 0.017
            },
            {
              "min": 318301,
              "max": 725050,
              "rate": 0.04
            },
            {
              "min": 725051,
              "max": 980100,
              "rate": 0.137
            },
            {
              "min": 980101,
              "max": 1467200,
              "rate": 0.168
            },
            {
              "min": 1467201,
              "max": null,
              "rate": 0.178
            }
          ],
          "description": "Additional 22% basic tax applies to net income."
        },
        {
          "id": "b47e4d88-066a-485f-ba69-57237fd40bc6",
          "name": "Corporate Income Tax",
          "type": "CIT",
          "rate": 22,
          "unit": "percent"
        }
      ]
    },
    {
      "name": "Ireland",
      "code": "IE",
      "currency": "EUR",
      "continent": "Europe",
      "essentialInfo": {
        "fiscalYear": "January to December",
        "taxAuthority": "National Revenue Authority",
        "filingDeadline": "Variable"
      },
      "taxes": [
        {
          "id": "83bba7dc-1a80-49ed-aaa3-220bec708810",
          "name": "Value Added Tax",
          "type": "VAT",
          "rate": 23,
          "unit": "percent"
        },
        {
          "id": "n4c5d6e7-f8a9-2n8p-1r0s-2l3m4n5p6r7s",
          "name": "Income Tax",
          "type": "PAYE",
          "rate": "20-40",
          "unit": "percent",
          "bands": [
            {
              "min": 0,
              "max": 44000,
              "rate": 0.2,
              "label": "Standard Rate"
            },
            {
              "min": 44001,
              "max": null,
              "rate": 0.4,
              "label": "Higher Rate"
            }
          ]
        },
        {
          "id": "o5d6e7f8-a9b0-3o9q-2s1t-3m4n5p6q7r8s",
          "name": "Corporation Tax (Trading)",
          "type": "CIT",
          "rate": 12.5,
          "unit": "percent"
        }
      ]
    },
    {
      "name": "Belgium",
      "code": "BE",
      "currency": "EUR",
      "continent": "Europe",
      "essentialInfo": {
        "fiscalYear": "January to December",
        "taxAuthority": "National Revenue Authority",
        "filingDeadline": "Variable"
      },
      "taxes": [
        {
          "id": "5568d449-9dd6-4cf7-bf2f-7915280a28a5",
          "name": "Value Added Tax",
          "type": "VAT",
          "rate": 21,
          "unit": "percent"
        },
        {
          "id": "p6e7f8a9-b0c1-4p0r-3t2u-4n5p6q7r8s9t",
          "name": "Personal Income Tax",
          "type": "PAYE",
          "rate": "25-50",
          "unit": "percent",
          "bands": [
            {
              "min": 0,
              "max": 16720,
              "rate": 0.25
            },
            {
              "min": 16721,
              "max": 29510,
              "rate": 0.4
            },
            {
              "min": 29511,
              "max": 51070,
              "rate": 0.45
            },
            {
              "min": 51071,
              "max": null,
              "rate": 0.5
            }
          ]
        },
        {
          "id": "babc2778-5b24-4bdc-8048-90e184f105dc",
          "name": "Corporate Income Tax",
          "type": "CIT",
          "rate": 25,
          "unit": "percent"
        }
      ]
    },
    {
      "name": "Austria",
      "code": "AT",
      "currency": "EUR",
      "continent": "Europe",
      "essentialInfo": {
        "fiscalYear": "January to December",
        "taxAuthority": "National Revenue Authority",
        "filingDeadline": "Variable"
      },
      "taxes": [
        {
          "id": "82f117c2-ef9c-4b0f-8310-c66fdb438d27",
          "name": "Value Added Tax",
          "type": "VAT",
          "rate": 20,
          "unit": "percent"
        },
        {
          "id": "r8g9h0i1-j2k3-6r0t-5v4w-6p7q8r9s0t1u",
          "name": "Income Tax",
          "type": "PAYE",
          "rate": "0-55",
          "unit": "percent",
          "bands": [
            {
              "min": 0,
              "max": 13541,
              "rate": 0
            },
            {
              "min": 13542,
              "max": 23562,
              "rate": 0.2
            },
            {
              "min": 23563,
              "max": 38167,
              "rate": 0.3
            },
            {
              "min": 38168,
              "max": 69213,
              "rate": 0.4
            },
            {
              "min": 69214,
              "max": 107954,
              "rate": 0.48
            },
            {
              "min": 107955,
              "max": null,
              "rate": 0.5
            }
          ]
        },
        {
          "id": "8b02b8b8-ce69-46ef-878a-37448788edc2",
          "name": "Corporate Income Tax",
          "type": "CIT",
          "rate": 23,
          "unit": "percent"
        }
      ]
    },
    {
      "name": "India",
      "code": "IN",
      "currency": "INR",
      "continent": "Asia",
      "essentialInfo": {
        "fiscalYear": "January to December",
        "taxAuthority": "National Revenue Authority",
        "filingDeadline": "Variable"
      },
      "taxes": [
        {
          "id": "db2a2f79-3ce1-492a-83e9-1737b97738ef",
          "name": "Goods and Services Tax (GST)",
          "type": "VAT",
          "rate": "5 | 18",
          "unit": "percent"
        },
        {
          "id": "u4v5w6x7-y8z9-0u1v-2w3x-4y5z6a7b8c9d",
          "name": "Income Tax (New Regime)",
          "type": "PAYE",
          "rate": "0-30",
          "unit": "percent",
          "bands": [
            {
              "min": 0,
              "max": 400000,
              "rate": 0
            },
            {
              "min": 400001,
              "max": 800000,
              "rate": 0.05
            },
            {
              "min": 800001,
              "max": 1200000,
              "rate": 0.1
            },
            {
              "min": 1200001,
              "max": 1600000,
              "rate": 0.15
            },
            {
              "min": 1600001,
              "max": 2000000,
              "rate": 0.2
            },
            {
              "min": 2000001,
              "max": 2400000,
              "rate": 0.25
            },
            {
              "min": 2400001,
              "max": null,
              "rate": 0.3
            }
          ]
        },
        {
          "id": "83a57f96-f54a-44c8-b48a-1e5cfe4314bd",
          "name": "Corporate Income Tax",
          "type": "CIT",
          "rate": 22,
          "unit": "percent"
        }
      ]
    },
    {
      "name": "China",
      "code": "CN",
      "currency": "CNY",
      "continent": "Asia",
      "essentialInfo": {
        "fiscalYear": "January to December",
        "taxAuthority": "National Revenue Authority",
        "filingDeadline": "Variable"
      },
      "taxes": [
        {
          "id": "5e089ca4-1cec-4c84-bee6-61f4238f064b",
          "name": "Value Added Tax (VAT)",
          "type": "VAT",
          "rate": 13,
          "unit": "percent"
        },
        {
          "id": "v5w6x7y8-z9a0-1v2w-3x4y-5z6a7b8c9d0e",
          "name": "Individual Income Tax (IIT)",
          "type": "PAYE",
          "rate": "3-45",
          "unit": "percent",
          "bands": [
            {
              "min": 0,
              "max": 36000,
              "rate": 0.03
            },
            {
              "min": 36001,
              "max": 144000,
              "rate": 0.1
            },
            {
              "min": 144001,
              "max": 300000,
              "rate": 0.2
            },
            {
              "min": 300001,
              "max": 420000,
              "rate": 0.25
            },
            {
              "min": 420001,
              "max": 660000,
              "rate": 0.3
            },
            {
              "min": 660001,
              "max": 960000,
              "rate": 0.35
            },
            {
              "min": 960001,
              "max": null,
              "rate": 0.45
            }
          ]
        },
        {
          "id": "525ad205-cab5-4963-b800-067305e26590",
          "name": "Corporate Income Tax",
          "type": "CIT",
          "rate": 25,
          "unit": "percent"
        }
      ]
    },
    {
      "name": "Japan",
      "code": "JP",
      "currency": "JPY",
      "continent": "Asia",
      "essentialInfo": {
        "fiscalYear": "January to December",
        "taxAuthority": "National Revenue Authority",
        "filingDeadline": "Variable"
      },
      "taxes": [
        {
          "id": "9d202186-2425-4eab-aa83-caf2ab5ca514",
          "name": "Consumption Tax (VAT)",
          "type": "VAT",
          "rate": 10,
          "unit": "percent"
        },
        {
          "id": "w6x7y8z9-a0b1-2w3x-4y5z-6a7b8c9d0e1f",
          "name": "Individual Income Tax (National)",
          "type": "PAYE",
          "rate": "5-45",
          "unit": "percent",
          "bands": [
            {
              "min": 0,
              "max": 1950000,
              "rate": 0.05
            },
            {
              "min": 1950001,
              "max": 3300000,
              "rate": 0.1
            },
            {
              "min": 3300001,
              "max": 6950000,
              "rate": 0.2
            },
            {
              "min": 6950001,
              "max": 9000000,
              "rate": 0.23
            },
            {
              "min": 9000001,
              "max": 18000000,
              "rate": 0.33
            },
            {
              "min": 18000001,
              "max": 40000000,
              "rate": 0.4
            },
            {
              "min": 40000001,
              "max": null,
              "rate": 0.45
            }
          ]
        },
        {
          "id": "4b8646a4-13d5-46ad-b90d-8fdc617e8af9",
          "name": "Corporate Income Tax (Effective Rate)",
          "type": "CIT",
          "rate": 31.5,
          "unit": "percent"
        }
      ]
    },
    {
      "name": "Singapore",
      "code": "SG",
      "currency": "SGD",
      "continent": "Asia",
      "essentialInfo": {
        "fiscalYear": "January to December",
        "taxAuthority": "National Revenue Authority",
        "filingDeadline": "Variable"
      },
      "taxes": [
        {
          "id": "fa9cb978-fb00-452d-bafd-b5469d8d65dd",
          "name": "Goods and Services Tax (GST)",
          "type": "VAT",
          "rate": 9,
          "unit": "percent"
        },
        {
          "id": "x7y8z9a0-b1c2-3x4y-5z6a-7b8c9d0e1f2g",
          "name": "Personal Income Tax",
          "type": "PAYE",
          "rate": "0-24",
          "unit": "percent",
          "bands": [
            {
              "min": 0,
              "max": 20000,
              "rate": 0
            },
            {
              "min": 20001,
              "max": 30000,
              "rate": 0.02
            },
            {
              "min": 30001,
              "max": 40000,
              "rate": 0.035
            },
            {
              "min": 40001,
              "max": 80000,
              "rate": 0.07
            },
            {
              "min": 80001,
              "max": 120000,
              "rate": 0.115
            },
            {
              "min": 120001,
              "max": 160000,
              "rate": 0.15
            },
            {
              "min": 160001,
              "max": 200000,
              "rate": 0.18
            },
            {
              "min": 200001,
              "max": 240000,
              "rate": 0.19
            },
            {
              "min": 240001,
              "max": 280000,
              "rate": 0.195
            },
            {
              "min": 280001,
              "max": 320000,
              "rate": 0.2
            },
            {
              "min": 320001,
              "max": 500000,
              "rate": 0.22
            },
            {
              "min": 500001,
              "max": 1000000,
              "rate": 0.23
            },
            {
              "min": 1000001,
              "max": null,
              "rate": 0.24
            }
          ]
        },
        {
          "id": "cf2d5c57-9c8a-4e60-9f4f-83719e5e61f5",
          "name": "Corporate Income Tax",
          "type": "CIT",
          "rate": 17,
          "unit": "percent"
        }
      ]
    },
    {
      "name": "UAE",
      "code": "AE",
      "currency": "AED",
      "continent": "Asia",
      "essentialInfo": {
        "fiscalYear": "January to December",
        "taxAuthority": "National Revenue Authority",
        "filingDeadline": "Variable"
      },
      "taxes": [
        {
          "id": "c70661a9-3409-43f7-b3e1-9b9d92ec2289",
          "name": "Value Added Tax (VAT)",
          "type": "VAT",
          "rate": 5,
          "unit": "percent"
        },
        {
          "id": "y8z9a0b1-c2d3-4y5z-6a7b-8c9d0e1f2g3h",
          "name": "Personal Income Tax",
          "type": "PAYE",
          "rate": 0,
          "unit": "percent"
        },
        {
          "id": "3fc16b4c-4021-4119-bfa4-048bb2d766a8",
          "name": "Corporate Tax",
          "type": "CIT",
          "rate": 9,
          "unit": "percent",
          "description": "0% for qualifying income up to AED 375,000."
        }
      ]
    },
    {
      "name": "Saudi Arabia",
      "code": "SA",
      "currency": "SAR",
      "continent": "Asia",
      "essentialInfo": {
        "fiscalYear": "January to December",
        "taxAuthority": "National Revenue Authority",
        "filingDeadline": "Variable"
      },
      "taxes": [
        {
          "id": "d596dd1b-8ee5-4423-a06b-b719790c7fd6",
          "name": "Value Added Tax (VAT)",
          "type": "VAT",
          "rate": 15,
          "unit": "percent"
        },
        {
          "id": "z9a0b1c2-d3e4-5z6a-7b8c-9d0e1f2g3h4i",
          "name": "Income Tax",
          "type": "PAYE",
          "rate": 0,
          "unit": "percent"
        },
        {
          "id": "4f4efd3c-855b-424d-8211-eed3a7e362a0",
          "name": "Corporate Income Tax",
          "type": "CIT",
          "rate": 20,
          "unit": "percent"
        }
      ]
    },
    {
      "name": "Israel",
      "code": "IL",
      "currency": "ILS",
      "continent": "Asia",
      "essentialInfo": {
        "fiscalYear": "January to December",
        "taxAuthority": "National Revenue Authority",
        "filingDeadline": "Variable"
      },
      "taxes": [
        {
          "id": "68a6b274-a3b5-4136-bc0e-607eca3e6f91",
          "name": "Value Added Tax (VAT)",
          "type": "VAT",
          "rate": 18,
          "unit": "percent",
          "description": "Increased from 17% to 18% effective January 1, 2025."
        },
        {
          "id": "a0b1c2d3-e4f5-6a7b-8c9d-0e1f2g3h4i5j",
          "name": "Personal Income Tax",
          "type": "PAYE",
          "rate": "10-50",
          "unit": "percent",
          "bands": [
            {
              "min": 0,
              "max": 84120,
              "rate": 0.1
            },
            {
              "min": 84121,
              "max": 120720,
              "rate": 0.14
            },
            {
              "min": 120721,
              "max": 193800,
              "rate": 0.2
            },
            {
              "min": 193801,
              "max": 269280,
              "rate": 0.31
            },
            {
              "min": 269281,
              "max": 560280,
              "rate": 0.35
            },
            {
              "min": 560281,
              "max": 721560,
              "rate": 0.47
            },
            {
              "min": 721561,
              "max": null,
              "rate": 0.5
            }
          ]
        },
        {
          "id": "56b8c355-87f1-4f8d-9f45-e70527cae404",
          "name": "Corporate Income Tax",
          "type": "CIT",
          "rate": 23,
          "unit": "percent"
        }
      ]
    },
    {
      "name": "South Korea",
      "code": "KR",
      "currency": "KRW",
      "continent": "Asia",
      "essentialInfo": {
        "fiscalYear": "January to December",
        "taxAuthority": "National Revenue Authority",
        "filingDeadline": "Variable"
      },
      "taxes": [
        {
          "id": "7e2dc056-d753-4d4f-85d2-5c8b389b2fea",
          "name": "Value Added Tax (VAT)",
          "type": "VAT",
          "rate": 10,
          "unit": "percent"
        },
        {
          "id": "b1c2d3e4-f5g6-7h8i-9j0k-1l2m3n4o5p6q",
          "name": "Individual Income Tax",
          "type": "PAYE",
          "rate": "6-45",
          "unit": "percent",
          "bands": [
            {
              "min": 0,
              "max": 14000000,
              "rate": 0.06
            },
            {
              "min": 14000001,
              "max": 50000000,
              "rate": 0.15
            },
            {
              "min": 50000001,
              "max": 88000000,
              "rate": 0.24
            },
            {
              "min": 88000001,
              "max": 150000000,
              "rate": 0.35
            },
            {
              "min": 150000001,
              "max": 300000000,
              "rate": 0.38
            },
            {
              "min": 300000001,
              "max": 500000000,
              "rate": 0.4
            },
            {
              "min": 500000001,
              "max": 1000000000,
              "rate": 0.42
            },
            {
              "min": 1000000001,
              "max": null,
              "rate": 0.45
            }
          ]
        },
        {
          "id": "fe5c21d1-cdeb-4d3f-b698-7f1885f9d0f5",
          "name": "Corporate Income Tax",
          "type": "CIT",
          "rate": "10-25",
          "unit": "percent",
          "description": "Progressive rates: 10%, 21%, 23%, 25% plus 1% surtax from 2026."
        }
      ]
    },
    {
      "name": "Thailand",
      "code": "TH",
      "currency": "THB",
      "continent": "Asia",
      "essentialInfo": {
        "fiscalYear": "January to December",
        "taxAuthority": "National Revenue Authority",
        "filingDeadline": "Variable"
      },
      "taxes": [
        {
          "id": "93d684df-1ece-4e85-a38f-8656ac8c14b4",
          "name": "Value Added Tax (VAT)",
          "type": "VAT",
          "rate": 7,
          "unit": "percent",
          "description": "Reduced rate of 7% extended until September 30, 2026."
        },
        {
          "id": "c2d3e4f5-g6h7-8i9j-0k1l-2m3n4o5p6q7r",
          "name": "Personal Income Tax",
          "type": "PAYE",
          "rate": "0-35",
          "unit": "percent",
          "bands": [
            {
              "min": 0,
              "max": 150000,
              "rate": 0
            },
            {
              "min": 150001,
              "max": 300000,
              "rate": 0.05
            },
            {
              "min": 300001,
              "max": 500000,
              "rate": 0.1
            },
            {
              "min": 500001,
              "max": 750000,
              "rate": 0.15
            },
            {
              "min": 750001,
              "max": 1000000,
              "rate": 0.2
            },
            {
              "min": 1000001,
              "max": 2000000,
              "rate": 0.25
            },
            {
              "min": 2000001,
              "max": 5000000,
              "rate": 0.3
            },
            {
              "min": 5000001,
              "max": null,
              "rate": 0.35
            }
          ]
        },
        {
          "id": "39846a8d-9b98-4841-bc45-d55b316ccd64",
          "name": "Corporate Income Tax",
          "type": "CIT",
          "rate": 20,
          "unit": "percent"
        }
      ]
    },
    {
      "name": "Vietnam",
      "code": "VN",
      "currency": "VND",
      "continent": "Asia",
      "essentialInfo": {
        "fiscalYear": "January to December",
        "taxAuthority": "National Revenue Authority",
        "filingDeadline": "Variable"
      },
      "taxes": [
        {
          "id": "5b398386-9a01-4a06-9e23-f79e7647cdf1",
          "name": "Value Added Tax (VAT)",
          "type": "VAT",
          "rate": 8,
          "unit": "percent",
          "description": "Temporarily reduced to 8% until December 31, 2026."
        },
        {
          "id": "d3e4f5g6-h7i8-9j0k-1l2m-3n4o5p6q7r8s",
          "name": "Personal Income Tax",
          "type": "PAYE",
          "rate": "5-35",
          "unit": "percent",
          "bands": [
            {
              "min": 0,
              "max": 60000000,
              "rate": 0.05
            },
            {
              "min": 60000001,
              "max": 120000000,
              "rate": 0.1
            },
            {
              "min": 120000001,
              "max": 216000000,
              "rate": 0.15
            },
            {
              "min": 216000001,
              "max": 384000000,
              "rate": 0.2
            },
            {
              "min": 384000001,
              "max": 624000000,
              "rate": 0.25
            },
            {
              "min": 624000001,
              "max": 960000000,
              "rate": 0.3
            },
            {
              "min": 960000001,
              "max": null,
              "rate": 0.35
            }
          ]
        },
        {
          "id": "d8839dca-5163-486e-820f-cf29dd5d547e",
          "name": "Corporate Income Tax",
          "type": "CIT",
          "rate": 20,
          "unit": "percent"
        }
      ]
    },
    {
      "name": "Portugal",
      "code": "PT",
      "currency": "EUR",
      "continent": "Europe",
      "essentialInfo": {
        "fiscalYear": "January to December",
        "taxAuthority": "National Revenue Authority",
        "filingDeadline": "Variable"
      },
      "taxes": [
        {
          "id": "32d76b80-d913-4586-aa44-e8774c2e6dd9",
          "name": "Value Added Tax",
          "type": "VAT",
          "rate": 23,
          "unit": "percent"
        },
        {
          "id": "t0i1j2k3-l4m5-8t2v-7x6y-8r9s0t1u2v3w",
          "name": "Income Tax (IRS)",
          "type": "PAYE",
          "rate": "12.5-48",
          "unit": "percent",
          "bands": [
            {
              "min": 0,
              "max": 8342,
              "rate": 0.125
            },
            {
              "min": 8343,
              "max": 12108,
              "rate": 0.167
            },
            {
              "min": 12109,
              "max": 17855,
              "rate": 0.2
            },
            {
              "min": 17856,
              "max": 23419,
              "rate": 0.232
            },
            {
              "min": 23420,
              "max": 29631,
              "rate": 0.3
            },
            {
              "min": 29632,
              "max": 40167,
              "rate": 0.327
            },
            {
              "min": 40168,
              "max": 51996,
              "rate": 0.37
            },
            {
              "min": 51997,
              "max": 86634,
              "rate": 0.45
            },
            {
              "min": 86635,
              "max": null,
              "rate": 0.48
            }
          ]
        },
        {
          "id": "858d1f0a-907d-469e-ae40-aab7bc8e15e0",
          "name": "Corporate Income Tax (IRC)",
          "type": "CIT",
          "rate": 19,
          "unit": "percent"
        }
      ]
    },
    {
      "name": "Greece",
      "code": "GR",
      "currency": "EUR",
      "continent": "Europe",
      "essentialInfo": {
        "fiscalYear": "January to December",
        "taxAuthority": "National Revenue Authority",
        "filingDeadline": "Variable"
      },
      "taxes": [
        {
          "id": "a4aa9c71-462c-47dc-a0d8-393cd987ef9d",
          "name": "Value Added Tax",
          "type": "VAT",
          "rate": 24,
          "unit": "percent"
        },
        {
          "id": "w3l4m5n6-o7p8-1w5y-0a1b-1u2v3w4x5y6z",
          "name": "Personal Income Tax",
          "type": "PAYE",
          "rate": "9-44",
          "unit": "percent",
          "bands": [
            {
              "min": 0,
              "max": 10000,
              "rate": 0.09
            },
            {
              "min": 10001,
              "max": 20000,
              "rate": 0.2
            },
            {
              "min": 20001,
              "max": 30000,
              "rate": 0.26
            },
            {
              "min": 30001,
              "max": 40000,
              "rate": 0.34
            },
            {
              "min": 40001,
              "max": 60000,
              "rate": 0.39
            },
            {
              "min": 60001,
              "max": null,
              "rate": 0.44
            }
          ]
        },
        {
          "id": "7450e7a8-fed4-4c54-bb20-c650b9420b8b",
          "name": "Corporate Income Tax",
          "type": "CIT",
          "rate": 22,
          "unit": "percent"
        }
      ]
    },
    {
      "name": "Denmark",
      "code": "DK",
      "currency": "DKK",
      "continent": "Europe",
      "essentialInfo": {
        "fiscalYear": "January to December",
        "taxAuthority": "National Revenue Authority",
        "filingDeadline": "Variable"
      },
      "taxes": [
        {
          "id": "ea02e0c9-bb75-4e55-84bc-d3db30634a61",
          "name": "Value Added Tax",
          "type": "VAT",
          "rate": 25,
          "unit": "percent"
        },
        {
          "id": "y5n6o7p8-q9r0-3y7a-2c3d-3w4x5y6z7a8b",
          "name": "State Income Tax",
          "type": "PAYE",
          "rate": "12-52",
          "unit": "percent",
          "bands": [
            {
              "min": 0,
              "max": 641200,
              "rate": 0.1201
            },
            {
              "min": 641201,
              "max": 777900,
              "rate": 0.1951
            },
            {
              "min": 777901,
              "max": 2592700,
              "rate": 0.1951
            },
            {
              "min": 2592701,
              "max": null,
              "rate": 0.2451
            }
          ]
        },
        {
          "id": "1abbaee5-fa2d-4304-a349-44e41ad67a83",
          "name": "Corporate Income Tax",
          "type": "CIT",
          "rate": 22,
          "unit": "percent"
        }
      ]
    },
    {
      "name": "Finland",
      "code": "FI",
      "currency": "EUR",
      "continent": "Europe",
      "essentialInfo": {
        "fiscalYear": "January to December",
        "taxAuthority": "National Revenue Authority",
        "filingDeadline": "Variable"
      },
      "taxes": [
        {
          "id": "57dd2fb9-e9e6-456e-a95c-701445f68240",
          "name": "Value Added Tax",
          "type": "VAT",
          "rate": 25.5,
          "unit": "percent"
        },
        {
          "id": "a7p8q9r0-s1t2-5a9c-4e5f-5y6z7a8b9c0d",
          "name": "State Income Tax",
          "type": "PAYE",
          "rate": "12.6-44.2",
          "unit": "percent",
          "bands": [
            {
              "min": 0,
              "max": 22000,
              "rate": 0.1264
            },
            {
              "min": 22001,
              "max": 52100,
              "rate": 0.19
            },
            {
              "min": 52101,
              "max": 80000,
              "rate": 0.3025
            },
            {
              "min": 80001,
              "max": 150000,
              "rate": 0.34
            },
            {
              "min": 150001,
              "max": null,
              "rate": 0.4425
            }
          ]
        },
        {
          "id": "0ddcfbbc-a0e9-4771-b57f-4c7fa8e0d225",
          "name": "Corporate Income Tax",
          "type": "CIT",
          "rate": 20,
          "unit": "percent"
        }
      ]
    },
    {
      "name": "Canada",
      "code": "CA",
      "currency": "CAD",
      "continent": "North America",
      "essentialInfo": {
        "fiscalYear": "January to December",
        "taxAuthority": "National Revenue Authority",
        "filingDeadline": "Variable"
      },
      "taxes": [
        {
          "id": "1dc9a9b4-55b6-412a-b42b-ff982df35a37",
          "name": "Goods and Services Tax (GST)",
          "type": "VAT",
          "rate": 5,
          "unit": "percent"
        },
        {
          "id": "c7d8e9f0-a1b2-1c2d-3e4f-5g6h7i8j9k0l",
          "name": "Federal Income Tax",
          "type": "PAYE",
          "rate": "14-33",
          "unit": "percent",
          "bands": [
            {
              "min": 0,
              "max": 58523,
              "rate": 0.14
            },
            {
              "min": 58524,
              "max": 117045,
              "rate": 0.205
            },
            {
              "min": 117046,
              "max": 181440,
              "rate": 0.26
            },
            {
              "min": 181441,
              "max": 258482,
              "rate": 0.29
            },
            {
              "min": 258483,
              "max": null,
              "rate": 0.33
            }
          ]
        },
        {
          "id": "7e5f4a2b-ba7b-441c-97d9-9050b3bd1d33",
          "name": "Corporate Income Tax (Net Federal)",
          "type": "CIT",
          "rate": 15,
          "unit": "percent"
        }
      ]
    },
    {
      "name": "Mexico",
      "code": "MX",
      "currency": "MXN",
      "continent": "North America",
      "essentialInfo": {
        "fiscalYear": "January to December",
        "taxAuthority": "National Revenue Authority",
        "filingDeadline": "Variable"
      },
      "taxes": [
        {
          "id": "2c1c6b42-a248-4603-a443-a473cc1f2f46",
          "name": "Value Added Tax (IVA)",
          "type": "VAT",
          "rate": 16,
          "unit": "percent"
        },
        {
          "id": "m5n6o7p8-q9r0-4m8s-3t4u-5v6w7x8y9z0a",
          "name": "Income Tax (ISR)",
          "type": "PAYE",
          "rate": "1.92-35",
          "unit": "percent",
          "bands": [
            {
              "min": 0,
              "max": 9400,
              "rate": 0.0192
            },
            {
              "min": 79000,
              "max": 138000,
              "rate": 0.1088
            },
            {
              "min": 500000,
              "max": 1000000,
              "rate": 0.3
            },
            {
              "min": 1000001,
              "max": null,
              "rate": 0.35
            }
          ],
          "description": "Simplified brackets based on 2026 projections."
        },
        {
          "id": "98e7b690-e17e-45e9-beaa-0b2f05c0428f",
          "name": "Corporate Income Tax",
          "type": "CIT",
          "rate": 30,
          "unit": "percent"
        }
      ]
    },
    {
      "name": "Brazil",
      "code": "BR",
      "currency": "BRL",
      "continent": "South America",
      "essentialInfo": {
        "fiscalYear": "January to December",
        "taxAuthority": "National Revenue Authority",
        "filingDeadline": "Variable"
      },
      "taxes": [
        {
          "id": "ba7cbbc6-ee8f-47c4-ad51-88e588df69ad",
          "name": "IBS/CBS (Dual VAT)",
          "type": "VAT",
          "rate": 1,
          "unit": "percent",
          "description": "Transition phase (0.9% CBS + 0.1% IBS) for 2026."
        },
        {
          "id": "n1p2q3r4-s5t6-9u8v-0w1x-1y2z3a4b5c6d",
          "name": "Personal Income Tax (IRPF)",
          "type": "PAYE",
          "rate": "0-27.5",
          "unit": "percent",
          "bands": [
            {
              "min": 0,
              "max": 33900,
              "rate": 0
            },
            {
              "min": 33901,
              "max": 45000,
              "rate": 0.075
            },
            {
              "min": 45001,
              "max": 55900,
              "rate": 0.15
            },
            {
              "min": 55901,
              "max": 67400,
              "rate": 0.225
            },
            {
              "min": 67401,
              "max": null,
              "rate": 0.275
            }
          ]
        },
        {
          "id": "1c75a57f-b3a9-4156-92fb-4b9a6cf765a3",
          "name": "Corporate Income Tax (Combined)",
          "type": "CIT",
          "rate": 34,
          "unit": "percent"
        }
      ]
    },
    {
      "name": "Argentina",
      "code": "AR",
      "currency": "ARS",
      "continent": "South America",
      "essentialInfo": {
        "fiscalYear": "January to December",
        "taxAuthority": "National Revenue Authority",
        "filingDeadline": "Variable"
      },
      "taxes": [
        {
          "id": "0a6f280e-4e84-4c57-ae52-c1a57694b52b",
          "name": "Value Added Tax (IVA)",
          "type": "VAT",
          "rate": 21,
          "unit": "percent"
        },
        {
          "id": "q4r5s6t7-u8v9-2q0w-1e2r-3t4y5u6i7o8p",
          "name": "Income Tax (Ganancias)",
          "type": "PAYE",
          "rate": "5-35",
          "unit": "percent",
          "bands": [
            {
              "min": 0,
              "max": 2000000,
              "rate": 0.05
            },
            {
              "min": 2000001,
              "max": 5000000,
              "rate": 0.15
            },
            {
              "min": 5000001,
              "max": null,
              "rate": 0.35
            }
          ]
        },
        {
          "id": "5ff5dd30-aecb-4f89-8be1-1140759d56b9",
          "name": "Corporate Income Tax",
          "type": "CIT",
          "rate": "25-35",
          "unit": "percent",
          "description": "Progressive rates based on net taxable income."
        }
      ]
    },
    {
      "name": "Colombia",
      "code": "CO",
      "currency": "COP",
      "continent": "South America",
      "essentialInfo": {
        "fiscalYear": "January to December",
        "taxAuthority": "National Revenue Authority",
        "filingDeadline": "Variable"
      },
      "taxes": [
        {
          "id": "891ff418-9756-4190-9b92-a9fed9dadeca",
          "name": "Value Added Tax (IVA)",
          "type": "VAT",
          "rate": 19,
          "unit": "percent"
        },
        {
          "id": "r5s6t7u8-v9w0-3r1x-2y3z-4a5s6d7f8g9h",
          "name": "Individual Income Tax",
          "type": "PAYE",
          "rate": "0-41",
          "unit": "percent",
          "bands": [
            {
              "min": 0,
              "max": 47000000,
              "rate": 0
            },
            {
              "min": 47000001,
              "max": 80000000,
              "rate": 0.19
            },
            {
              "min": 80000001,
              "max": 170000000,
              "rate": 0.28
            },
            {
              "min": 170000001,
              "max": 350000000,
              "rate": 0.35
            },
            {
              "min": 350000001,
              "max": null,
              "rate": 0.41
            }
          ]
        },
        {
          "id": "96719f38-f2f4-4bf1-bc49-1d495dd09d03",
          "name": "Corporate Income Tax",
          "type": "CIT",
          "rate": 35,
          "unit": "percent"
        }
      ]
    },
    {
      "name": "Chile",
      "code": "CL",
      "currency": "CLP",
      "continent": "South America",
      "essentialInfo": {
        "fiscalYear": "January to December",
        "taxAuthority": "National Revenue Authority",
        "filingDeadline": "Variable"
      },
      "taxes": [
        {
          "id": "61b19a6f-9343-400e-b97f-d0ac2b706e4f",
          "name": "Value Added Tax (IVA)",
          "type": "VAT",
          "rate": 19,
          "unit": "percent"
        },
        {
          "id": "s6t7u8v9-w0x1-4s2y-3z4a-5b6n7m8k9l0p",
          "name": "Global Complementario (Personal Income Tax)",
          "type": "PAYE",
          "rate": "0-35.5",
          "unit": "percent",
          "bands": [
            {
              "min": 0,
              "max": 10500000,
              "rate": 0
            },
            {
              "min": 10500001,
              "max": 23000000,
              "rate": 0.04
            },
            {
              "min": 23000001,
              "max": 38000000,
              "rate": 0.08
            },
            {
              "min": 38000001,
              "max": 54000000,
              "rate": 0.135
            },
            {
              "min": 54000001,
              "max": 72000000,
              "rate": 0.23
            },
            {
              "min": 72000001,
              "max": 96000000,
              "rate": 0.304
            },
            {
              "min": 96000001,
              "max": null,
              "rate": 0.355
            }
          ]
        },
        {
          "id": "a8d1f91b-8537-466e-9fd2-d45116a5a0a5",
          "name": "Corporate Income Tax (Partially Integrated)",
          "type": "CIT",
          "rate": 27,
          "unit": "percent"
        }
      ]
    },
    {
      "name": "Peru",
      "code": "PE",
      "currency": "PEN",
      "continent": "South America",
      "essentialInfo": {
        "fiscalYear": "January to December",
        "taxAuthority": "National Revenue Authority",
        "filingDeadline": "Variable"
      },
      "taxes": [
        {
          "id": "806242d4-c431-4ec4-a041-b41c513fc1ce",
          "name": "General Sales Tax (IGV)",
          "type": "VAT",
          "rate": 18,
          "unit": "percent",
          "description": "Comprises 14% IGV and 4% IPM starting 2026."
        },
        {
          "id": "t7u8v9w0-x1y2-5t3z-4a5b-6c7d8e9f0g1h",
          "name": "Income Tax",
          "type": "PAYE",
          "rate": "8-30",
          "unit": "percent",
          "bands": [
            {
              "min": 0,
              "max": 27500,
              "rate": 0.08
            },
            {
              "min": 27501,
              "max": 110000,
              "rate": 0.14
            },
            {
              "min": 110001,
              "max": 192500,
              "rate": 0.17
            },
            {
              "min": 192501,
              "max": 247500,
              "rate": 0.2
            },
            {
              "min": 247501,
              "max": null,
              "rate": 0.3
            }
          ]
        },
        {
          "id": "6fcaa507-b289-4c9e-bb4d-ff2db757904f",
          "name": "Corporate Income Tax",
          "type": "CIT",
          "rate": 29.5,
          "unit": "percent"
        }
      ]
    },
    {
      "name": "Australia",
      "code": "AU",
      "currency": "AUD",
      "continent": "Oceania",
      "essentialInfo": {
        "fiscalYear": "July to June",
        "taxAuthority": "Australian Taxation Office (ATO)",
        "filingDeadline": "October 31"
      },
      "taxes": [
        {
          "id": "e4f5g6h7-i8j9-0k1l-2m3n-4o5p6q7r8s9t",
          "name": "Goods and Services Tax (GST)",
          "type": "VAT",
          "rate": 10,
          "unit": "percent"
        },
        {
          "id": "f5g6h7i8-j9k0-1l2m-3n4o-5p6q7r8s9t0u",
          "name": "Personal Income Tax",
          "type": "PAYE",
          "rate": "0-45",
          "unit": "percent",
          "bands": [
            {
              "min": 0,
              "max": 18200,
              "rate": 0,
              "label": "Tax-free threshold"
            },
            {
              "min": 18201,
              "max": 45000,
              "rate": 0.16,
              "label": "16% rate (FY 2025-26)"
            },
            {
              "min": 45001,
              "max": 135000,
              "rate": 0.3
            },
            {
              "min": 135001,
              "max": 190000,
              "rate": 0.37
            },
            {
              "min": 190001,
              "max": null,
              "rate": 0.45
            }
          ],
          "description": "Excludes 2% Medicare Levy."
        },
        {
          "id": "76620ca9-3cb9-4c57-8106-9bd6814bb289",
          "name": "Corporate Income Tax",
          "type": "CIT",
          "rate": 25,
          "unit": "percent",
          "description": "25% for base rate entities, 30% for others."
        }
      ]
    },
    {
      "name": "New Zealand",
      "code": "NZ",
      "currency": "NZD",
      "continent": "Oceania",
      "essentialInfo": {
        "fiscalYear": "April to March",
        "taxAuthority": "Inland Revenue Department (IRD)",
        "filingDeadline": "July 7"
      },
      "taxes": [
        {
          "id": "g6h7i8j9-k0l1-2m3n-4o5p-6q7r8s9t0u1v",
          "name": "Goods and Services Tax (GST)",
          "type": "VAT",
          "rate": 15,
          "unit": "percent"
        },
        {
          "id": "h7i8j9k0-l1m2-3n4o-5p6q-7r8s9t0u1v2w",
          "name": "Personal Income Tax",
          "type": "PAYE",
          "rate": "10.5-39",
          "unit": "percent",
          "bands": [
            {
              "min": 0,
              "max": 15600,
              "rate": 0.105
            },
            {
              "min": 15601,
              "max": 53500,
              "rate": 0.175
            },
            {
              "min": 53501,
              "max": 78100,
              "rate": 0.3
            },
            {
              "min": 78101,
              "max": 180000,
              "rate": 0.33
            },
            {
              "min": 180001,
              "max": null,
              "rate": 0.39
            }
          ]
        },
        {
          "id": "67cb2a6b-c73d-425b-ae0e-6f81b16ee91e",
          "name": "Corporate Income Tax",
          "type": "CIT",
          "rate": 28,
          "unit": "percent"
        }
      ]
    }
  ],
  "meta": {
    "version": "1.3.0",
    "lastUpdated": "2026-03-17"
  }
}